usieg/__init__.py
usieg/__main__.py
usieg/arpf1.py
usieg/edge.py
usieg/formatter/__init__.py
usieg/formatter/audition.py
usieg/formatter/rttm.py
usieg/formatter/time_formatter.py
usieg/main_cli.py
usieg/statistics/__init__.py
usieg/statistics/audio_len.py
usieg-0.1.0.dist-info/entry_points.txt
usieg-0.1.0.dist-info/METADATA
usieg-0.1.0.dist-info/WHEEL
usieg-0.1.0.dist-info/RECORD
