Metadata-Version: 2.1
Name: usieg
Version: 0.1.0
Summary: 
Author: migo
Author-email: 1695587905@qq.com
Requires-Python: >=3.10,<4.0
Classifier: Programming Language :: Python :: 3
Classifier: Programming Language :: Python :: 3.10
Classifier: Programming Language :: Python :: 3.11
Classifier: Programming Language :: Python :: 3.12
Classifier: Programming Language :: Python :: 3.13
Requires-Dist: numpy (<=2.1.3)
Requires-Dist: pandas (<=2.2.3)
Requires-Dist: soundfile (>=0.12.1,<0.13.0)
Requires-Dist: textgrid (>=1.6.1,<2.0.0)
Requires-Dist: tqdm (>=4.67.1,<5.0.0)
Requires-Dist: typer (>=0.15.1,<0.16.0)
